counter.v
`timescale 1ns / 1ps
module counter (
		input clk, rst,
		output reg [3:0] ctrl, output reg [7:0] segment
);

integer i, j;       //temporary values 
reg clkdiv, clkdiv2; 
reg [2:0] flag; 
reg [3:0] first;    //digits (units)
reg [3:0] second;   //(tens)
reg [3:0] third;    //(hundreds)
reg [3:0] fourth;   //(thousands)

initial begin
		i = 0;
		j = 0;
		first = 4'b0000;
		second = 4'b0000;
		third = 4'b000;
		fourth = 4'b000;
		clkdiv = 1'b0;
		clkdiv2 = 1'b0;
		flag = 1'b0;
end

always @(posedge clk) begin  //4MHz clock (Spartan 6 FPGA)
		i = i+1; j = j+1;
		if (i == 1000) begin //i == 2000000 for 4MHz clock (depends on the FPGA clock). Keep it low for simulation (1000)
			clkdiv = ~clkdiv;
			i = 0;
		end
		if (j == 1) begin    //j == 2000 for the multiplexed 7-segment display. Keep it low for simulation(1)
			clkdiv2 = ~clkdiv2;
			j = 0;
		end
end
 
always @(posedge clkdiv) begin  //1Hz clock (increased frequency)
	if (rst == 1'b1) begin
		first = 4'b0000;
		second = 4'b0000;
		third = 4'b000;
		fourth = 4'b000;
	end
	else begin
		first = first+1;
		if (first == 4'd10) begin
			first = 4'd0;
			second = second+1; 
		end
		if (second == 4'd10) begin
			second = 4'd0;
			third = third+1;
		end
		if (third == 4'd10) begin
			third = 4'd0;
			fourth = fourth+1;
		end
	end
end

always@(posedge clkdiv2) begin
	if (flag == 2'b00) begin
		ctrl = 4'b0111;     //controls which of the four 7-segments display
		case (first)
			4'd0:segment=8'b11111100;
			4'd1:segment=8'b01100000;
			4'd2:segment=8'b11011010;  
			4'd3:segment=8'b11110010; 
			4'd4:segment=8'b01100110; 
			4'd5:segment=8'b10110110; 
			4'd6:segment=8'b10111110; 
			4'd7:segment=8'b11100000; 
			4'd8:segment=8'b11111110; 
			4'd9:segment=8'b11110110;  
		endcase
		flag = 2'b01;
	end
	else if (flag == 2'b01) begin
		ctrl = 4'b1011;
		case (second)
			4'd0:segment=8'b11111100;
			4'd1:segment=8'b01100000; 
			4'd2:segment=8'b11011010;  
			4'd3:segment=8'b11110010; 
			4'd4:segment=8'b01100110; 
			4'd5:segment=8'b10110110; 
			4'd6:segment=8'b10111110; 
			4'd7:segment=8'b11100000; 
			4'd8:segment=8'b11111110; 
			4'd9:segment=8'b11110110;         
		endcase
		flag = 2'b10;
	end
	else if (flag == 2'b10) begin
		ctrl = 4'b1101;
		case (third)
			4'd0:segment=8'b11111100;
			4'd1:segment=8'b01100000; 
			4'd2:segment=8'b11011010;  
			4'd3:segment=8'b11110010; 
			4'd4:segment=8'b01100110; 
			4'd5:segment=8'b10110110; 
			4'd6:segment=8'b10111110; 
			4'd7:segment=8'b11100000; 
			4'd8:segment=8'b11111110; 
			4'd9:segment=8'b11110110;         
		endcase
		flag = 2'b11;
	end
	else begin
		ctrl = 4'b1110;
		case (fourth)
			4'd0:segment=8'b11111100;
			4'd1:segment=8'b01100000; 
			4'd2:segment=8'b11011010;  
			4'd3:segment=8'b11110010; 
			4'd4:segment=8'b01100110; 
			4'd5:segment=8'b10110110; 
			4'd6:segment=8'b10111110; 
			4'd7:segment=8'b11100000; 
			4'd8:segment=8'b11111110; 
			4'd9:segment=8'b11110110;         
		endcase
		flag = 2'b00;
	end
end

endmodule

testbench.v
`timescale 1ns / 1ps
module testbench;

    reg clk,rst;
    wire [3:0] ctrl ;
    wire [7:0] segment;

    counter dut(clk, rst, ctrl, segment);

    always #1 clk = ~clk;

    initial begin
        $dumpfile("testbench.vcd");
        $dumpvars(0,testbench);
        clk <= 1'b0;
        $monitor("ctrl = %d, segment = %d\n",ctrl,segment);
    end

    initial #100000 $finish; //100k clock pulses

endmodule

testbench.vcd
$date
	Fri Oct 06 20:11:13 2023
$end
$version
	Icarus Verilog
$end
$timescale
	1ps
$end
$scope module testbench $end
$var wire 8 ! segment [7:0] $end
$var wire 4 " ctrl [3:0] $end
$var reg 1 # clk $end
$var reg 1 $ rst $end
$scope module dut $end
$var wire 1 # clk $end
$var wire 1 $ rst $end
$var reg 1 % clkdiv $end
$var reg 1 & clkdiv2 $end
$var reg 4 ' ctrl [3:0] $end
$var reg 4 ( first [3:0] $end
$var reg 3 ) flag [2:0] $end
$var reg 4 * fourth [3:0] $end
$var reg 4 + second [3:0] $end
$var reg 8 , segment [7:0] $end
$var reg 4 - third [3:0] $end
$var integer 32 . i [31:0] $end
$var integer 32 / j [31:0] $end
$upscope $end
$upscope $end
$enddefinitions $end
$comment Show the parameter values. $end
$dumpall
$end
#0
$dumpvars
b0 /
b0 .
b0 -
bx ,
b0 +
b0 *
b0 )
b0 (
bx '
0&
0%
x$
0#
bx "
bx !
$end
#1000
b1 )
b11111100 !
b11111100 ,
b111 "
b111 '
1&
b0 /
b1 .
1#
#2000
0#
#3000
0&
b0 /
b10 .
1#
#4000
0#
#5000
b10 )
b1011 "
b1011 '
1&
b0 /
b11 .
1#
#6000
0#
#7000
0&
b0 /
b100 .
1#
#8000
0#
#9000
b11 )
b1101 "
b1101 '
1&
b0 /
b101 .
1#
#10000
0#
#11000
0&
b0 /
b110 .
1#
#12000
0#
#13000
b0 )
b1110 "
b1110 '
1&
b0 /
b111 .
1#
#14000
0#
#15000
0&
b0 /
b1000 .
1#
#16000
0#
#17000
b1 )
b111 "
b111 '
1&
b0 /
b1001 .
1#
#18000
0#
#19000
0&
b0 /
b1010 .
1#
#20000
0#
#21000
b10 )
b1011 "
b1011 '
1&
b0 /
b1011 .
1#
#22000
0#
#23000
0&
b0 /
b1100 .
1#
#24000
0#
#25000
b11 )
b1101 "
b1101 '
1&
b0 /
b1101 .
1#
#26000
0#
#27000
0&
b0 /
b1110 .
1#
#28000
0#
#29000
b0 )
b1110 "
b1110 '
1&
b0 /
b1111 .
1#
#30000
0#
#31000
0&
b0 /
b10000 .
1#
#32000
0#
#33000
b1 )
b111 "
b111 '
1&
b0 /
b10001 .
1#
#34000
0#
#35000
0&
b0 /
b10010 .
1#
#36000
0#
#37000
b10 )
b1011 "
b1011 '
1&
b0 /
b10011 .
1#
#38000
0#
#39000
0&
b0 /
b10100 .
1#
#40000
0#
#41000
b11 )
b1101 "
b1101 '
1&
b0 /
b10101 .
1#
#42000
0#
#43000
0&
b0 /
b10110 .
1#
#44000
0#
#45000
b0 )
b1110 "
b1110 '
1&
b0 /
b10111 .
1#
#46000
0#
#47000
0&
b0 /
b11000 .
1#
#48000
0#
#49000
b1 )
b111 "
b111 '
1&
b0 /
b11001 .
1#
#50000
0#
#51000
0&
b0 /
b11010 .
1#
#52000
0#
#53000
b10 )
b1011 "
b1011 '
1&
b0 /
b11011 .
1#
#54000
0#
#55000
0&
b0 /
b11100 .
1#
#56000
0#
#57000
b11 )
b1101 "
b1101 '
1&
b0 /
b11101 .
1#
#58000
0#
#59000
0&
b0 /
b11110 .
1#
#60000
0#
#61000
b0 )
b1110 "
b1110 '
1&
b0 /
b11111 .
1#
#62000
0#
#63000
0&
b0 /
b100000 .
1#
#64000
0#
#65000
b1 )
b111 "
b111 '
1&
b0 /
b100001 .
1#
#66000
0#
#67000
0&
b0 /
b100010 .
1#
#68000
0#
#69000
b10 )
b1011 "
b1011 '
1&
b0 /
b100011 .
1#
#70000
0#
#71000
0&
b0 /
b100100 .
1#
#72000
0#
#73000
b11 )
b1101 "
b1101 '
1&
b0 /
b100101 .
1#
#74000
0#
#75000
0&
b0 /
b100110 .
1#
#76000
0#
#77000
b0 )
b1110 "
b1110 '
1&
b0 /
b100111 .
1#
#78000
0#
#79000
0&
b0 /
b101000 .
1#
#80000
0#
#81000
b1 )
b111 "
b111 '
1&
b0 /
b101001 .
1#
#82000
0#
#83000
0&
b0 /
b101010 .
1#
#84000
0#
#85000
b10 )
b1011 "
b1011 '
1&
b0 /
b101011 .
1#
#86000
0#
#87000
0&
b0 /
b101100 .
1#
#88000
0#
#89000
b11 )
b1101 "
b1101 '
1&
b0 /
b101101 .
1#
#90000
0#
#91000
0&
b0 /
b101110 .
1#
#92000
0#
#93000
b0 )
b1110 "
b1110 '
1&
b0 /
b101111 .
1#
#94000
0#
#95000
0&
b0 /
b110000 .
1#
#96000
0#
#97000
b1 )
b111 "
b111 '
1&
b0 /
b110001 .
1#
#98000
0#
#99000
0&
b0 /
b110010 .
1#
#100000
0#
#101000
b10 )
b1011 "
b1011 '
1&
b0 /
b110011 .
1#
#102000
0#
#103000
0&
b0 /
b110100 .
1#
#104000
0#
#105000
b11 )
b1101 "
b1101 '
1&
b0 /
b110101 .
1#
#106000
0#
#107000
0&
b0 /
b110110 .
1#
#108000
0#
#109000
b0 )
b1110 "
b1110 '
1&
b0 /
b110111 .
1#
#110000
0#
#111000
0&
b0 /
b111000 .
1#
#112000
0#
#113000
b1 )
b111 "
b111 '
1&
b0 /
b111001 .
1#
#114000
0#
#115000
0&
b0 /
b111010 .
1#
#116000
0#
#117000
b10 )
b1011 "
b1011 '
1&
b0 /
b111011 .
1#
#118000
0#
#119000
0&
b0 /
b111100 .
1#
#120000
0#
#121000
b11 )
b1101 "
b1101 '
1&
b0 /
b111101 .
1#
#122000
0#
#123000
0&
b0 /
b111110 .
1#
#124000
0#
#125000
b0 )
b1110 "
b1110 '
1&
b0 /
b111111 .
1#
#126000
0#
#127000
0&
b0 /
b1000000 .
1#
#128000
0#
#129000
b1 )
b111 "
b111 '
1&
b0 /
b1000001 .
1#
#130000
0#
#131000
0&
b0 /
b1000010 .
1#
#132000
0#
#133000
b10 )
b1011 "
b1011 '
1&
b0 /
b1000011 .
1#
#134000
0#
#135000
0&
b0 /
b1000100 .
1#
#136000
0#
#137000
b11 )
b1101 "
b1101 '
1&
b0 /
b1000101 .
1#
#138000
0#
#139000
0&
b0 /
b1000110 .
1#
#140000
0#
#141000
b0 )
b1110 "
b1110 '
1&
b0 /
b1000111 .
1#
#142000
0#
#143000
0&
b0 /
b1001000 .
1#
#144000
0#
#145000
b1 )
b111 "
b111 '
1&
b0 /
b1001001 .
1#
#146000
0#
#147000
0&
b0 /
b1001010 .
1#
#148000
0#
#149000
b10 )
b1011 "
b1011 '
1&
b0 /
b1001011 .
1#
#150000
0#
#151000
0&
b0 /
b1001100 .
1#
#152000
0#
#153000
b11 )
b1101 "
b1101 '
1&
b0 /
b1001101 .
1#
#154000
0#
#155000
0&
b0 /
b1001110 .
1#
#156000
0#
#157000
b0 )
b1110 "
b1110 '
1&
b0 /
b1001111 .
1#
#158000
0#
#159000
0&
b0 /
b1010000 .
1#
#160000
0#
#161000
b1 )
b111 "
b111 '
1&
b0 /
b1010001 .
1#
#162000
0#
#163000
0&
b0 /
b1010010 .
1#
#164000
0#
#165000
b10 )
b1011 "
b1011 '
1&
b0 /
b1010011 .
1#
#166000
0#
#167000
0&
b0 /
b1010100 .
1#
#168000
0#
#169000
b11 )
b1101 "
b1101 '
1&
b0 /
b1010101 .
1#
#170000
0#
#171000
0&
b0 /
b1010110 .
1#
#172000
0#
#173000
b0 )
b1110 "
b1110 '
1&
b0 /
b1010111 .
1#
#174000
0#
#175000
0&
b0 /
b1011000 .
1#
#176000
0#
#177000
b1 )
b111 "
b111 '
1&
b0 /
b1011001 .
1#
#178000
0#
#179000
0&
b0 /
b1011010 .
1#
#180000
0#
#181000
b10 )
b1011 "
b1011 '
1&
b0 /
b1011011 .
1#
#182000
0#
#183000
0&
b0 /
b1011100 .
1#
#184000
0#
#185000
b11 )
b1101 "
b1101 '
1&
b0 /
b1011101 .
1#
#186000
0#
#187000
0&
b0 /
b1011110 .
1#
#188000
0#
#189000
b0 )
b1110 "
b1110 '
1&
b0 /
b1011111 .
1#
#190000
0#
#191000
0&
b0 /
b1100000 .
1#
#192000
0#
#193000
b1 )
b111 "
b111 '
1&
b0 /
b1100001 .
1#
#194000
0#
#195000
0&
b0 /
b1100010 .
1#
#196000
0#
#197000
b10 )
b1011 "
b1011 '
1&
b0 /
b1100011 .
1#
#198000
0#
#199000
0&
b0 /
b1100100 .
1#
#200000
0#
#201000
b11 )
b1101 "
b1101 '
1&
b0 /
b1100101 .
1#
#202000
0#
#203000
0&
b0 /
b1100110 .
1#
#204000
0#
#205000
b0 )
b1110 "
b1110 '
1&
b0 /
b1100111 .
1#
#206000
0#
#207000
0&
b0 /
b1101000 .
1#
#208000
0#
#209000
b1 )
b111 "
b111 '
1&
b0 /
b1101001 .
1#
#210000
0#
#211000
0&
b0 /
b1101010 .
1#
#212000
0#
#213000
b10 )
b1011 "
b1011 '
1&
b0 /
b1101011 .
1#
#214000
0#
#215000
0&
b0 /
b1101100 .
1#
#216000
0#
#217000
b11 )
b1101 "
b1101 '
1&
b0 /
b1101101 .
1#
#218000
0#
#219000
0&
b0 /
b1101110 .
1#
#220000
0#
#221000
b0 )
b1110 "
b1110 '
1&
b0 /
b1101111 .
1#
#222000
0#
#223000
0&
b0 /
b1110000 .
1#
#224000
0#
#225000
b1 )
b111 "
b111 '
1&
b0 /
b1110001 .
1#
#226000
0#
#227000
0&
b0 /
b1110010 .
1#
#228000
0#
#229000
b10 )
b1011 "
b1011 '
1&
b0 /
b1110011 .
1#
#230000
0#
#231000
0&
b0 /
b1110100 .
1#
#232000
0#
#233000
b11 )
b1101 "
b1101 '
1&
b0 /
b1110101 .
1#
#234000
0#
#235000
0&
b0 /
b1110110 .
1#
#236000
0#
#237000
b0 )
b1110 "
b1110 '
1&
b0 /
b1110111 .
1#
#238000
0#
#239000
0&
b0 /
b1111000 .
1#
#240000
0#
#241000
b1 )
b111 "
b111 '
1&
b0 /
b1111001 .
1#
#242000
0#
#243000
0&
b0 /
b1111010 .
1#
#244000
0#
#245000
b10 )
b1011 "
b1011 '
1&
b0 /
b1111011 .
1#
#246000
0#
#247000
0&
b0 /
b1111100 .
1#
#248000
0#
#249000
b11 )
b1101 "
b1101 '
1&
b0 /
b1111101 .
1#
#250000
0#
#251000
0&
b0 /
b1111110 .
1#
#252000
0#
#253000
b0 )
b1110 "
b1110 '
1&
b0 /
b1111111 .
1#
#254000
0#
#255000
0&
b0 /
b10000000 .
1#
#256000
0#
#257000
b1 )
b111 "
b111 '
1&
b0 /
b10000001 .
1#
#258000
0#
#259000
0&
b0 /
b10000010 .
1#
#260000
0#
#261000
b10 )
b1011 "
b1011 '
1&
b0 /
b10000011 .
1#
#262000
0#
#263000
0&
b0 /
b10000100 .
1#
#264000
0#
#265000
b11 )
b1101 "
b1101 '
1&
b0 /
b10000101 .
1#
#266000
0#
#267000
0&
b0 /
b10000110 .
1#
#268000
0#
#269000
b0 )
b1110 "
b1110 '
1&
b0 /
b10000111 .
1#
#270000
0#
#271000
0&
b0 /
b10001000 .
1#
#272000
0#
#273000
b1 )
b111 "
b111 '
1&
b0 /
b10001001 .
1#
#274000
0#
#275000
0&
b0 /
b10001010 .
1#
#276000
0#
#277000
b10 )
b1011 "
b1011 '
1&
b0 /
b10001011 .
1#
#278000
0#
#279000
0&
b0 /
b10001100 .
1#
#280000
0#
#281000
b11 )
b1101 "
b1101 '
1&
b0 /
b10001101 .
1#
#282000
0#
#283000
0&
b0 /
b10001110 .
1#
#284000
0#
#285000
b0 )
b1110 "
b1110 '
1&
b0 /
b10001111 .
1#
#286000
0#
#287000
0&
b0 /
b10010000 .
1#
#288000
0#
#289000
b1 )
b111 "
b111 '
1&
b0 /
b10010001 .
1#
#290000
0#
#291000
0&
b0 /
b10010010 .
1#
#292000
0#
#293000
b10 )
b1011 "
b1011 '
1&
b0 /
b10010011 .
1#
#294000
0#
#295000
0&
b0 /
b10010100 .
1#
#296000
0#
#297000
b11 )
b1101 "
b1101 '
1&
b0 /
b10010101 .
1#
#298000
0#
#299000
0&
b0 /
b10010110 .
1#
#300000
0#
#301000
b0 )
b1110 "
b1110 '
1&
b0 /
b10010111 .
1#
#302000
0#
#303000
0&
b0 /
b10011000 .
1#
#304000
0#
#305000
b1 )
b111 "
b111 '
1&
b0 /
b10011001 .
1#
#306000
0#
#307000
0&
b0 /
b10011010 .
1#
#308000
0#
#309000
b10 )
b1011 "
b1011 '
1&
b0 /
b10011011 .
1#
#310000
0#
#311000
0&
b0 /
b10011100 .
1#
#312000
0#
#313000
b11 )
b1101 "
b1101 '
1&
b0 /
b10011101 .
1#
#314000
0#
#315000
0&
b0 /
b10011110 .
1#
#316000
0#
#317000
b0 )
b1110 "
b1110 '
1&
b0 /
b10011111 .
1#
#318000
0#
#319000
0&
b0 /
b10100000 .
1#
#320000
0#
#321000
b1 )
b111 "
b111 '
1&
b0 /
b10100001 .
1#
#322000
0#
#323000
0&
b0 /
b10100010 .
1#
#324000
0#
#325000
b10 )
b1011 "
b1011 '
1&
b0 /
b10100011 .
1#
#326000
0#
#327000
0&
b0 /
b10100100 .
1#
#328000
0#
#329000
b11 )
b1101 "
b1101 '
1&
b0 /
b10100101 .
1#
#330000
0#
#331000
0&
b0 /
b10100110 .
1#
#332000
0#
#333000
b0 )
b1110 "
b1110 '
1&
b0 /
b10100111 .
1#
#334000
0#
#335000
0&
b0 /
b10101000 .
1#
#336000
0#
#337000
b1 )
b111 "
b111 '
1&
b0 /
b10101001 .
1#
#338000
0#
#339000
0&
b0 /
b10101010 .
1#
#340000
0#
#341000
b10 )
b1011 "
b1011 '
1&
b0 /
b10101011 .
1#
#342000
0#
#343000
0&
b0 /
b10101100 .
1#
#344000
0#
#345000
b11 )
b1101 "
b1101 '
1&
b0 /
b10101101 .
1#
#346000
0#
#347000
0&
b0 /
b10101110 .
1#
#348000
0#
#349000
b0 )
b1110 "
b1110 '
1&
b0 /
b10101111 .
1#
#350000
0#
#351000
0&
b0 /
b10110000 .
1#
#352000
0#
#353000
b1 )
b111 "
b111 '
1&
b0 /
b10110001 .
1#
#354000
0#
#355000
0&
b0 /
b10110010 .
1#
#356000
0#
#357000
b10 )
b1011 "
b1011 '
1&
b0 /
b10110011 .
1#
#358000
0#
#359000
0&
b0 /
b10110100 .
1#
#360000
0#
#361000
b11 )
b1101 "
b1101 '
1&
b0 /
b10110101 .
1#
#362000
0#
#363000
0&
b0 /
b10110110 .
1#
#364000
0#
#365000
b0 )
b1110 "
b1110 '
1&
b0 /
b10110111 .
1#
#366000
0#
#367000
0&
b0 /
b10111000 .
1#
#368000
0#
#369000
b1 )
b111 "
b111 '
1&
b0 /
b10111001 .
1#
#370000
0#
#371000
0&
b0 /
b10111010 .
1#
#372000
0#
#373000
b10 )
b1011 "
b1011 '
1&
b0 /
b10111011 .
1#
#374000
0#
#375000
0&
b0 /
b10111100 .
1#
#376000
0#
#377000
b11 )
b1101 "
b1101 '
1&
b0 /
b10111101 .
1#
#378000
0#
#379000
0&
b0 /
b10111110 .
1#
#380000
0#
#381000
b0 )
b1110 "
b1110 '
1&
b0 /
b10111111 .
1#
#382000
0#
#383000
0&
b0 /
b11000000 .
1#
#384000
0#
#385000
b1 )
b111 "
b111 '
1&
b0 /
b11000001 .
1#
#386000
0#
#387000
0&
b0 /
b11000010 .
1#
#388000
0#
#389000
b10 )
b1011 "
b1011 '
1&
b0 /
b11000011 .
1#
#390000
0#
#391000
0&
b0 /
b11000100 .
1#
#392000
0#
#393000
b11 )
b1101 "
b1101 '
1&
b0 /
b11000101 .
1#
#394000
0#
#395000
0&
b0 /
b11000110 .
1#
#396000
0#
#397000
b0 )
b1110 "
b1110 '
1&
b0 /
b11000111 .
1#
#398000
0#
#399000
0&
b0 /
b11001000 .
1#
#400000
0#
#401000
b1 )
b111 "
b111 '
1&
b0 /
b11001001 .
1#
#402000
0#
#403000
0&
b0 /
b11001010 .
1#
#404000
0#
#405000
b10 )
b1011 "
b1011 '
1&
b0 /
b11001011 .
1#
#406000
0#
#407000
0&
b0 /
b11001100 .
1#
#408000
0#
#409000
b11 )
b1101 "
b1101 '
1&
b0 /
b11001101 .
1#
#410000
0#
#411000
0&
b0 /
b11001110 .
1#
#412000
0#
#413000
b0 )
b1110 "
b1110 '
1&
b0 /
b11001111 .
1#
#414000
0#
#415000
0&
b0 /
b11010000 .
1#
#416000
0#
#417000
b1 )
b111 "
b111 '
1&
b0 /
b11010001 .
1#
#418000
0#
#419000
0&
b0 /
b11010010 .
1#
#420000
0#
#421000
b10 )
b1011 "
b1011 '
1&
b0 /
b11010011 .
1#
#422000
0#
#423000
0&
b0 /
b11010100 .
1#
#424000
0#
#425000
b11 )
b1101 "
b1101 '
1&
b0 /
b11010101 .
1#
#426000
0#
#427000
0&
b0 /
b11010110 .
1#
#428000
0#
#429000
b0 )
b1110 "
b1110 '
1&
b0 /
b11010111 .
1#
#430000
0#
#431000
0&
b0 /
b11011000 .
1#
#432000
0#
#433000
b1 )
b111 "
b111 '
1&
b0 /
b11011001 .
1#
#434000
0#
#435000
0&
b0 /
b11011010 .
1#
#436000
0#
#437000
b10 )
b1011 "
b1011 '
1&
b0 /
b11011011 .
1#
#438000
0#
#439000
0&
b0 /
b11011100 .
1#
#440000
0#
#441000
b11 )
b1101 "
b1101 '
1&
b0 /
b11011101 .
1#
#442000
0#
#443000
0&
b0 /
b11011110 .
1#
#444000
0#
#445000
b0 )
b1110 "
b1110 '
1&
b0 /
b11011111 .
1#
#446000
0#
#447000
0&
b0 /
b11100000 .
1#
#448000
0#
#449000
b1 )
b111 "
b111 '
1&
b0 /
b11100001 .
1#
#450000
0#
#451000
0&
b0 /
b11100010 .
1#
#452000
0#
#453000
b10 )
b1011 "
b1011 '
1&
b0 /
b11100011 .
1#
#454000
0#
#455000
0&
b0 /
b11100100 .
1#
#456000
0#
#457000
b11 )
b1101 "
b1101 '
1&
b0 /
b11100101 .
1#
#458000
0#
#459000
0&
b0 /
b11100110 .
1#
#460000
0#
#461000
b0 )
b1110 "
b1110 '
1&
b0 /
b11100111 .
1#
#462000
0#
#463000
0&
b0 /
b11101000 .
1#
#464000
0#
#465000
b1 )
b111 "
b111 '
1&
b0 /
b11101001 .
1#
#466000
0#
#467000
0&
b0 /
b11101010 .
1#
#468000
0#
#469000
b10 )
b1011 "
b1011 '
1&
b0 /
b11101011 .
1#
#470000
0#
#471000
0&
b0 /
b11101100 .
1#
#472000
0#
#473000
b11 )
b1101 "
b1101 '
1&
b0 /
b11101101 .
1#
#474000
0#
#475000
0&
b0 /
b11101110 .
1#
#476000
0#
#477000
b0 )
b1110 "
b1110 '
1&
b0 /
b11101111 .
1#
#478000
0#
#479000
0&
b0 /
b11110000 .
1#
#480000
0#
#481000
b1 )
b111 "
b111 '
1&
b0 /
b11110001 .
1#
#482000
0#
#483000
0&
b0 /
b11110010 .
1#
#484000
0#
#485000
b10 )
b1011 "
b1011 '
1&
b0 /
b11110011 .
1#
#486000
0#
#487000
0&
b0 /
b11110100 .
1#
#488000
0#
#489000
b11 )
b1101 "
b1101 '
1&
b0 /
b11110101 .
1#
#490000
0#
#491000
0&
b0 /
b11110110 .
1#
#492000
0#
#493000
b0 )
b1110 "
b1110 '
1&
b0 /
b11110111 .
1#
#494000
0#
#495000
0&
b0 /
b11111000 .
1#
#496000
0#
#497000
b1 )
b111 "
b111 '
1&
b0 /
b11111001 .
1#
#498000
0#
#499000
0&
b0 /
b11111010 .
1#
#500000
0#
#501000
b10 )
b1011 "
b1011 '
1&
b0 /
b11111011 .
1#
#502000
0#
#503000
0&
b0 /
b11111100 .
1#
#504000
0#
#505000
b11 )
b1101 "
b1101 '
1&
b0 /
b11111101 .
1#
#506000
0#
#507000
0&
b0 /
b11111110 .
1#
#508000
0#
#509000
b0 )
b1110 "
b1110 '
1&
b0 /
b11111111 .
1#
#510000
0#
#511000
0&
b0 /
b100000000 .
1#
#512000
0#
#513000
b1 )
b111 "
b111 '
1&
b0 /
b100000001 .
1#
#514000
0#
#515000
0&
b0 /
b100000010 .
1#
#516000
0#
#517000
b10 )
b1011 "
b1011 '
1&
b0 /
b100000011 .
1#
#518000
0#
#519000
0&
b0 /
b100000100 .
1#
#520000
0#
#521000
b11 )
b1101 "
b1101 '
1&
b0 /
b100000101 .
1#
#522000
0#
#523000
0&
b0 /
b100000110 .
1#
#524000
0#
#525000
b0 )
b1110 "
b1110 '
1&
b0 /
b100000111 .
1#
#526000
0#
#527000
0&
b0 /
b100001000 .
1#
#528000
0#
#529000
b1 )
b111 "
b111 '
1&
b0 /
b100001001 .
1#
#530000
0#
#531000
0&
b0 /
b100001010 .
1#
#532000
0#
#533000
b10 )
b1011 "
b1011 '
1&
b0 /
b100001011 .
1#
#534000
0#
#535000
0&
b0 /
b100001100 .
1#
#536000
0#
#537000
b11 )
b1101 "
b1101 '
1&
b0 /
b100001101 .
1#
#538000
0#
#539000
0&
b0 /
b100001110 .
1#
#540000
0#
#541000
b0 )
b1110 "
b1110 '
1&
b0 /
b100001111 .
1#
#542000
0#
#543000
0&
b0 /
b100010000 .
1#
#544000
0#
#545000
b1 )
b111 "
b111 '
1&
b0 /
b100010001 .
1#
#546000
0#
#547000
0&
b0 /
b100010010 .
1#
#548000
0#
#549000
b10 )
b1011 "
b1011 '
1&
b0 /
b100010011 .
1#
#550000
0#
#551000
0&
b0 /
b100010100 .
1#
#552000
0#
#553000
b11 )
b1101 "
b1101 '
1&
b0 /
b100010101 .
1#
#554000
0#
#555000
0&
b0 /
b100010110 .
1#
#556000
0#
#557000
b0 )
b1110 "
b1110 '
1&
b0 /
b100010111 .
1#
#558000
0#
#559000
0&
b0 /
b100011000 .
1#
#560000
0#
#561000
b1 )
b111 "
b111 '
1&
b0 /
b100011001 .
1#
#562000
0#
#563000
0&
b0 /
b100011010 .
1#
#564000
0#
#565000
b10 )
b1011 "
b1011 '
1&
b0 /
b100011011 .
1#
#566000
0#
#567000
0&
b0 /
b100011100 .
1#
#568000
0#
#569000
b11 )
b1101 "
b1101 '
1&
b0 /
b100011101 .
1#
#570000
0#
#571000
0&
b0 /
b100011110 .
1#
#572000
0#
#573000
b0 )
b1110 "
b1110 '
1&
b0 /
b100011111 .
1#
#574000
0#
#575000
0&
b0 /
b100100000 .
1#
#576000
0#
#577000
b1 )
b111 "
b111 '
1&
b0 /
b100100001 .
1#
#578000
0#
#579000
0&
b0 /
b100100010 .
1#
#580000
0#
#581000
b10 )
b1011 "
b1011 '
1&
b0 /
b100100011 .
1#
#582000
0#
#583000
0&
b0 /
b100100100 .
1#
#584000
0#
#585000
b11 )
b1101 "
b1101 '
1&
b0 /
b100100101 .
1#
#586000
0#
#587000
0&
b0 /
b100100110 .
1#
#588000
0#
#589000
b0 )
b1110 "
b1110 '
1&
b0 /
b100100111 .
1#
#590000
0#
#591000
0&
b0 /
b100101000 .
1#
#592000
0#
#593000
b1 )
b111 "
b111 '
1&
b0 /
b100101001 .
1#
#594000
0#
#595000
0&
b0 /
b100101010 .
1#
#596000
0#
#597000
b10 )
b1011 "
b1011 '
1&
b0 /
b100101011 .
1#
#598000
0#
#599000
0&
b0 /
b100101100 .
1#
#600000
0#
#601000
b11 )
b1101 "
b1101 '
1&
b0 /
b100101101 .
1#
#602000
0#
#603000
0&
b0 /
b100101110 .
1#
#604000
0#
#605000
b0 )
b1110 "
b1110 '
1&
b0 /
b100101111 .
1#
#606000
0#
#607000
0&
b0 /
b100110000 .
1#
#608000
0#
#609000
b1 )
b111 "
b111 '
1&
b0 /
b100110001 .
1#
#610000
0#
#611000
0&
b0 /
b100110010 .
1#
#612000
0#
#613000
b10 )
b1011 "
b1011 '
1&
b0 /
b100110011 .
1#
#614000
0#
#615000
0&
b0 /
b100110100 .
1#
#616000
0#
#617000
b11 )
b1101 "
b1101 '
1&
b0 /
b100110101 .
1#
#618000
0#
#619000
0&
b0 /
b100110110 .
1#
#620000
0#
#621000
b0 )
b1110 "
b1110 '
1&
b0 /
b100110111 .
1#
#622000
0#
#623000
0&
b0 /
b100111000 .
1#
#624000
0#
#625000
b1 )
b111 "
b111 '
1&
b0 /
b100111001 .
1#
#626000
0#
#627000
0&
b0 /
b100111010 .
1#
#628000
0#
#629000
b10 )
b1011 "
b1011 '
1&
b0 /
b100111011 .
1#
#630000
0#
#631000
0&
b0 /
b100111100 .
1#
#632000
0#
#633000
b11 )
b1101 "
b1101 '
1&
b0 /
b100111101 .
1#
#634000
0#
#635000
0&
b0 /
b100111110 .
1#
#636000
0#
#637000
b0 )
b1110 "
b1110 '
1&
b0 /
b100111111 .
1#
#638000
0#
#639000
0&
b0 /
b101000000 .
1#
#640000
0#
#641000
b1 )
b111 "
b111 '
1&
b0 /
b101000001 .
1#
#642000
0#
#643000
0&
b0 /
b101000010 .
1#
#644000
0#
#645000
b10 )
b1011 "
b1011 '
1&
b0 /
b101000011 .
1#
#646000
0#
#647000
0&
b0 /
b101000100 .
1#
#648000
0#
#649000
b11 )
b1101 "
b1101 '
1&
b0 /
b101000101 .
1#
#650000
0#
#651000
0&
b0 /
b101000110 .
1#
#652000
0#
#653000
b0 )
b1110 "
b1110 '
1&
b0 /
b101000111 .
1#
#654000
0#
#655000
0&
b0 /
b101001000 .
1#
#656000
0#
#657000
b1 )
b111 "
b111 '
1&
b0 /
b101001001 .
1#
#658000
0#
#659000
0&
b0 /
b101001010 .
1#
#660000
0#
#661000
b10 )
b1011 "
b1011 '
1&
b0 /
b101001011 .
1#
#662000
0#
#663000
0&
b0 /
b101001100 .
1#
#664000
0#
#665000
b11 )
b1101 "
b1101 '
1&
b0 /
b101001101 .
1#
#666000
0#
#667000
0&
b0 /
b101001110 .
1#
#668000
0#
#669000
b0 )
b1110 "
b1110 '
1&
b0 /
b101001111 .
1#
#670000
0#
#671000
0&
b0 /
b101010000 .
1#
#672000
0#
#673000
b1 )
b111 "
b111 '
1&
b0 /
b101010001 .
1#
#674000
0#
#675000
0&
b0 /
b101010010 .
1#
#676000
0#
#677000
b10 )
b1011 "
b1011 '
1&
b0 /
b101010011 .
1#
#678000
0#
#679000
0&
b0 /
b101010100 .
1#
#680000
0#
